CPU/DataMemory/Data_memory.v
/**********************************************************
    Data Memory Module
    stores data in memory
    reads data from memory

************************************************************/



//`timescale 1ns/100ps
// Data Memory Module
module Data_Memory (
    input               Read,         // Memory read signal
    input               Write,        // Memory write signal
    input               Clock,        // Clock signal
    input               Reset,        // Reset signal
    input [31:0]        Address,      // Address input (word address)
    input [31:0]        Write_data,   // Data to write
    input [2:0]         Func3,        // Function field for data type (byte, halfword, word)
    output reg [31:0]   Read_data,    // Data read output
    output reg          busywait      // Busywait signal
);

    // Memory array: 1024 words (32 bits each)
    reg [31:0] memory [0:1023];

    // Internal signals for detecting read/write access
    reg read_access, write_access;

    // Detect memory access
    always @(Read, Write) begin
        busywait = (Read || Write) ? 1 : 0;
        read_access = (Read && !Write) ? 1 : 0;
        write_access = (!Read && Write) ? 1 : 0;
    end

    // Memory read operation
    always @(posedge Clock) begin
        if (read_access) begin
            case (Func3)
                3'b000: // LB (Load Byte - Signed)
                    Read_data = {{24{memory[Address[31:2]][(Address[1:0] * 8) + 7]}}, memory[Address[31:2]][Address[1:0] * 8 +: 8]};
                3'b001: // LH (Load Halfword - Signed)
                    Read_data = {{16{memory[Address[31:2]][(Address[1] * 16) + 15]}}, memory[Address[31:2]][Address[1] * 16 +: 16]};
                3'b010: // LW (Load Word)
                    Read_data = memory[Address[31:2]];
                3'b100: // LBU (Load Byte - Unsigned)
                    Read_data = {24'b0, memory[Address[31:2]][Address[1:0] * 8 +: 8]};
                3'b101: // LHU (Load Halfword - Unsigned)
                    Read_data = {16'b0, memory[Address[31:2]][Address[1] * 16 +: 16]};
                default: // Default case for unsupported Func3
                    Read_data = 32'b0;
            endcase
            busywait = 0;
            read_access = 0;
        end
    end

    // Memory write operation
    always @(posedge Clock) begin
        if (write_access) begin
            case (Func3)
                3'b000: // SB (Store Byte)
                    memory[Address[31:2]][Address[1:0] * 8 +: 8] = Write_data[7:0];
                3'b001: // SH (Store Halfword)
                    memory[Address[31:2]][Address[1] * 16 +: 16] = Write_data[15:0];
                3'b010: // SW (Store Word)
                    memory[Address[31:2]] = Write_data;
            endcase
            busywait = 0;
            write_access = 0;
        end
    end

    // Reset memory
    integer i;
    always @(posedge Reset) begin
        if (Reset) begin
            for (i = 0; i < 1024; i = i + 1)
                memory[i] = 0;
            busywait = 0;
            read_access = 0;
            write_access = 0;
        end
    end

    // Optionally, print memory values when a write or read occurs (for debugging)
    always @(posedge Clock) begin
        if (write_access) begin
            $display("Writing data %h to Address %h", Write_data, Address);
            $display("Memory at Address %h: %h", Address, memory[Address[31:2]]);
        end
        if (read_access) begin
            $display("Reading data from Address %h: %h", Address, Read_data);
        end
    end
endmodule

CPU/DataMemory/Data_Memory_tb.v
// Testbench for Data Memory Module with LB, LH, LW, SH, SB, SW
module Data_Memory_tb;
    // Inputs
    reg Read;
    reg Write;
    reg Clock;
    reg Reset;
    reg [31:0] Address;
    reg [31:0] Write_data;
    reg [2:0] Func3;

    // Outputs
    wire [31:0] Read_data;
    wire busywait;

    // Instantiate the Data Memory Module
    Data_Memory uut (
        .Read(Read),
        .Write(Write),
        .Clock(Clock),
        .Reset(Reset),
        .Address(Address),
        .Write_data(Write_data),
        .Func3(Func3),
        .Read_data(Read_data),
        .busywait(busywait)
    );

    // Clock generation
    always #5 Clock = ~Clock;

    // Initialize the simulation and VCD file for GTKWave
    initial begin
        // Create a VCD dump file for GTKWave
        $dumpfile("data_memory_tb.vcd");  // File name for VCD dump
        $dumpvars(0, Data_Memory_tb);     // Dump all signals in the testbench

        // Initialize inputs
        Clock = 0;
        Reset = 1;
        Read = 0;
        Write = 0;
        Address = 0;
        Write_data = 0;
        Func3 = 0;

        // Reset memory
        #10 Reset = 0;

        // Test case 1: Store a word
        Address = 32'h00000004; // Address = 4
        Write_data = 32'h12345678; // Data to write
        Func3 = 3'b010; // SW (Store Word)
        Write = 1; #10 Write = 0;

        // Test case 2: Load the word
        Read = 1; Func3 = 3'b010; #10 Read = 0;

        // Test case 3: Store a byte
        Address = 32'h00000005; // Address = 5
        Write_data = 32'h000000AA; // Data to write (only byte is considered)
        Func3 = 3'b000; // SB (Store Byte)
        Write = 1; #10 Write = 0;

        // Test case 4: Load the byte (LB)
        Read = 1; Func3 = 3'b000; #10 Read = 0;

        // Test case 5: Store a halfword
        Address = 32'h00000006; // Address = 6
        Write_data = 32'h0000BBBB; // Data to write (only halfword is considered)
        Func3 = 3'b001; // SH (Store Halfword)
        Write = 1; #10 Write = 0;

        // Test case 6: Load the halfword (LH)
        Read = 1; Func3 = 3'b001; #10 Read = 0;

        // Test case 7: Store a word (SW)
        Address = 32'h00000010; // Address = 16
        Write_data = 32'hDEADBEEF; // Data to write
        Func3 = 3'b010; // SW (Store Word)
        Write = 1; #10 Write = 0;

        // Test case 8: Load the word (LW)
        Read = 1; Func3 = 3'b010; #10 Read = 0;

        // Finish simulation
        #50 $finish;
    end

    // Monitor signals
    initial begin
        $monitor("Time = %0t | Read = %b | Write = %b | Address = %h | Write_data = %h | Read_data = %h | Func3 = %b | busywait = %b", 
                 $time, Read, Write, Address, Write_data, Read_data, Func3, busywait);
    end
endmodule

CPU/DataMemory/data_memory_tb.vcd
$date
	Mon Jan 13 14:42:58 2025
$end
$version
	Icarus Verilog
$end
$timescale
	1s
$end
$scope module Data_Memory_tb $end
$var wire 32 ! Read_data [31:0] $end
$var wire 1 " busywait $end
$var reg 32 # Address [31:0] $end
$var reg 1 $ Clock $end
$var reg 3 % Func3 [2:0] $end
$var reg 1 & Read $end
$var reg 1 ' Reset $end
$var reg 1 ( Write $end
$var reg 32 ) Write_data [31:0] $end
$scope module uut $end
$var wire 32 * Address [31:0] $end
$var wire 1 + Clock $end
$var wire 3 , Func3 [2:0] $end
$var wire 1 - Read $end
$var wire 1 . Reset $end
$var wire 1 / Write $end
$var wire 32 0 Write_data [31:0] $end
$var reg 32 1 Read_data [31:0] $end
$var reg 1 2 busywait $end
$var integer 32 3 i [31:0] $end
$var reg 1 4 read_access $end
$var reg 1 5 write_access $end
$upscope $end
$upscope $end
$enddefinitions $end
#0
$dumpvars
05
04
b10000000000 3
02
bx 1
b0 0
0/
1.
0-
b0 ,
0+
b0 *
b0 )
0(
1'
0&
b0 %
0$
b0 #
0"
bx !
$end
#5
1$
1+
#10
15
12
1"
0$
0+
1(
1/
b10 %
b10 ,
b10010001101000101011001111000 )
b10010001101000101011001111000 0
b100 #
b100 *
0'
0.
#15
05
02
0"
1$
1+
#20
14
12
1"
0$
0+
1&
1-
0(
0/
#25
04
02
0"
b10010001101000101011001111000 1
b10010001101000101011001111000 !
1$
1+
#30
15
12
1"
0$
0+
1(
1/
b0 %
b0 ,
b10101010 )
b10101010 0
b101 #
b101 *
0&
0-
#35
05
02
0"
1$
1+
#40
14
12
1"
0$
0+
1&
1-
0(
0/
#45
04
02
0"
b11111111111111111111111110101010 1
b11111111111111111111111110101010 !
1$
1+
#50
15
12
1"
0$
0+
1(
1/
b1 %
b1 ,
b1011101110111011 )
b1011101110111011 0
b110 #
b110 *
0&
0-
#55
05
02
0"
1$
1+
#60
14
12
1"
0$
0+
1&
1-
0(
0/
#65
04
02
0"
b11111111111111111011101110111011 1
b11111111111111111011101110111011 !
1$
1+
#70
15
12
1"
0$
0+
1(
1/
b10 %
b10 ,
b11011110101011011011111011101111 )
b11011110101011011011111011101111 0
b10000 #
b10000 *
0&
0-
#75
05
02
0"
1$
1+
#80
14
12
1"
0$
0+
1&
1-
0(
0/
#85
04
02
0"
b11011110101011011011111011101111 1
b11011110101011011011111011101111 !
1$
1+
#90
0$
0+
0&
0-
